{
    "status": "ok",
    "datas": [
        {
            "id": "292940",
            "uid": "380942",
            "name": "",
            "title": "接触\r\n邂逅",
            "excerpt": "旅行中，大山大河，却比不过人与人接触后所产生的火花。每一段邂逅，每一眼，每一句，都引人遐想并留下深刻印象。而简·莫里斯选择了将他们清楚地描述出来。",
            "lead": "我一生旅行、写作，却很少写人。在我那些往往辞藻华丽的散 文中，地点、环境、历史出现的频率要高得多。但无论怎样，各地 的人才是激发我写作灵感的火花，哪怕我对他们的了解通常都只是蜻蜓点水—望向窗外的一眼、偶尔听到的温柔声音、双手间的触 碰—绝大多数都是这样短暂而难以捉摸的瞬间，它们散落在长达半个世纪的时间长河和四十多本著作中，我在这里是要心怀感激地将他们清楚地描述出来。 ——简·莫里斯 ",
            "model": "1",
            "position": "0",
            "thumbnail": "http://img.owspace.com/Public/uploads/Picture/2016-09-30/57ee28a44ffe7.jpg",
            "create_time": "1475544540",
            "update_time": "2016/10/04",
            "tags": [
                {
                    "name": "简·莫里斯"
                },
                {
                    "name": "游记"
                },
                {
                    "name": "接触"
                }
            ],
            "status": "1",
            "video": "",
            "fm": "",
            "link_url": "",
            "publish_time": "0",
            "view": "8.1w",
            "share": "http://static.owspace.com/wap/292940.html",
            "comment": "33",
            "good": "44",
            "bookmark": "0",
            "show_uid": "380942",
            "fm_play": "",
            "lunar_type": "1",
            "html5": "http://static.owspace.com/wap/292940.html",
            "author": "简·莫里斯 ",
            "tpl": 1,
            "avatar": "http://img.owspace.com/Public/static/avatar/1.png",
            "discover": "0",
            "category": "TO READ",
            "hot_comments": [],
            "parseXML": 1
        },
        {
            "id": "292927",
            "uid": "380029",
            "name": "",
            "title": "机场\r\n旅行",
            "excerpt": "对大多数人而言，机场是旅行的出发地和中转站，对德波顿而言，机场也可以是旅行的目的地。出发，就是抵达。而这趟旅行，每一个细节都透露着诗意和哲思。",
            "lead": "在这个混乱纷杂的时代，航站楼显然是秩序和逻辑的庇护所，不仅值得敬重，也引人好奇。航站楼是当代文化的想象中心。如果有人要你带火星人参观一个地方，其中简洁扼要地综合了人类文明中的各种主题——从我们对科技的信心，到我们对自然的摧残，以及从人类的紧密联系，到我们赋予旅行的浪漫色彩——那么这个地方必然是机场的出入境大厅。——阿兰·德波顿",
            "model": "1",
            "position": "0",
            "thumbnail": "http://img.owspace.com/Public/uploads/Picture/2016-09-29/57ecbaa633954.jpg",
            "create_time": "1475366400",
            "update_time": "2016/10/02",
            "tags": [
                {
                    "name": "阿兰·德波顿"
                },
                {
                    "name": "机场旅行"
                }
            ],
            "status": "1",
            "video": "",
            "fm": "",
            "link_url": "",
            "publish_time": "0",
            "view": "7.3w",
            "share": "http://static.owspace.com/wap/292927.html",
            "comment": "23",
            "good": "41",
            "bookmark": "0",
            "show_uid": "380029",
            "fm_play": "",
            "lunar_type": "1",
            "html5": "http://static.owspace.com/wap/292927.html",
            "author": "阿兰·德波顿 ",
            "tpl": 1,
            "avatar": "http://img.owspace.com/Public/static/avatar/4.png",
            "discover": "0",
            "category": "TO READ",
            "hot_comments": [],
            "parseXML": 1
        },
        {
            "id": "292873",
            "uid": "371380",
            "name": "",
            "title": "博尔赫斯的\r\n私人阅读",
            "excerpt": "博尔赫斯自称是“敏感而心怀感激的读者”，他的书单即是在文学之外记述自身。对于同为读者的你我，一辈子的所读书就是一个人的记忆和历史。",
            "lead": "让别人去夸耀写出的书好了，我则要为我读过的书而自诩。我不知道自己是不是个好作家，但我相信我是一个极好的读者；不管怎么说，我是一个敏感而心怀感激的读者。——博尔赫斯",
            "model": "1",
            "position": "0",
            "thumbnail": "http://img.owspace.com/Public/uploads/Picture/2016-09-19/57dfae3aa57fb.jpg",
            "create_time": "1474329600",
            "update_time": "2016/09/20",
            "tags": [
                {
                    "name": "博尔赫斯"
                },
                {
                    "name": "书单"
                }
            ],
            "status": "1",
            "video": "",
            "fm": "",
            "link_url": "",
            "publish_time": "0",
            "view": "7w",
            "share": "http://static.owspace.com/wap/292873.html",
            "comment": "15",
            "good": "29",
            "bookmark": "0",
            "show_uid": "371380",
            "fm_play": "",
            "lunar_type": "1",
            "html5": "http://static.owspace.com/wap/292873.html",
            "author": "博尔赫斯",
            "tpl": 1,
            "avatar": "http://img.owspace.com/Public/static/avatar/2.png",
            "discover": "0",
            "category": "TO READ",
            "hot_comments": [],
            "parseXML": 1
        },
        {
            "id": "292819",
            "uid": "363522",
            "name": "",
            "title": "别把我与所有人混为一谈",
            "excerpt": "在自我被高扬的时代，也许应该重回尼采。目空一切，既是天才又是疯子的他，循着习惯、本能之骄傲，提出并回答了“我是谁”。\r\n",
            "lead": "你们尚未曾寻找自己：你们就找到了我。所有信徒都是这样做的；因此一切信仰都是如此无关紧要。\r\n现在我要叫你们丢掉我，去寻找你们自己；唯当你们把我全部否弃时，我才意愿回到你们身边…… ——尼采",
            "model": "1",
            "position": "0",
            "thumbnail": "http://img.owspace.com/Public/uploads/Picture/2016-09-11/57d438d8df3c2.jpg",
            "create_time": "1473638400",
            "update_time": "2016/09/12",
            "tags": [
                {
                    "name": "尼采"
                },
                {
                    "name": "自传"
                }
            ],
            "status": "1",
            "video": "",
            "fm": "",
            "link_url": "",
            "publish_time": "0",
            "view": "9.6w",
            "share": "http://static.owspace.com/wap/292819.html",
            "comment": "31",
            "good": "39",
            "bookmark": "0",
            "show_uid": "363522",
            "fm_play": "",
            "lunar_type": "1",
            "html5": "http://static.owspace.com/wap/292819.html",
            "author": "尼采",
            "tpl": 1,
            "avatar": "http://img.owspace.com/Public/static/avatar/4.png",
            "discover": "0",
            "category": "TO READ",
            "hot_comments": [],
            "parseXML": 1
        },
        {
            "id": "292742",
            "uid": "290169",
            "name": "",
            "title": "加缪手记",
            "excerpt": "《局外人》在出版之初就以离经叛道的创作风格引发了巨大的争议，对此，加缪将自己对社会议论的回应写进手札，完成了对这部伟大作品的二次创作。",
            "lead": "《加缪手记》收录了加缪自 1935 年至 1959 年的读书杂感与生活随想，这些来自作家内心的细微声音如吉光片羽，为加缪提供着创作的灵感和对生命的思考。本文选自《加缪手记》第二卷，本卷写于加缪创作的黄金时期，读者可以从中看到《局外人》所遭逢的社会议论，《反抗者》出版后引起的激烈笔战，以及加缪创作风格与心路历程的变迁。",
            "model": "1",
            "position": "0",
            "thumbnail": "http://img.owspace.com/Public/uploads/Picture/2016-08-31/57c69e510276e.jpg",
            "create_time": "1472689020",
            "update_time": "2016/09/01",
            "tags": [
                {
                    "name": "加缪"
                },
                {
                    "name": "日记"
                }
            ],
            "status": "1",
            "video": "",
            "fm": "",
            "link_url": "",
            "publish_time": "0",
            "view": "8w",
            "share": "http://static.owspace.com/wap/292742.html",
            "comment": "27",
            "good": "38",
            "bookmark": "0",
            "show_uid": "290169",
            "fm_play": "",
            "lunar_type": "1",
            "html5": "http://static.owspace.com/wap/292742.html",
            "author": "阿尔贝·加缪",
            "tpl": 1,
            "avatar": "http://img.owspace.com/Public/static/avatar/2.png",
            "discover": "0",
            "category": "TO READ",
            "hot_comments": [],
            "parseXML": 1
        },
        {
            "id": "292590",
            "uid": "340875",
            "name": "",
            "title": "出轨",
            "excerpt": "不合时宜的甜蜜，道德枷锁下隐秘的情欲，并非“婚外情”的全部。爱尔兰作家威廉·特雷弗，在道德观之外，重新解释了这种危险的感情。",
            "lead": "他们拥抱时，百货公司橱窗的一块玻璃映照出他们的身姿。他们没注意到，玻璃中的这个影像在那短暂的瞬间记录下一种潇洒新潮的形象风貌；如果他们看到了，他和她多半会否认那是他们所呈示出的时尚风度，或者，他们也可能会猜测，在这场已成往事的婚外情缘中，他们确曾有过如此的刹那风华。",
            "model": "1",
            "position": "0",
            "thumbnail": "http://img.owspace.com/Public/uploads/Picture/2016-08-22/57bad1b9575fe.jpg",
            "create_time": "1471910400",
            "update_time": "2016/08/23",
            "tags": [
                {
                    "name": "出轨"
                }
            ],
            "status": "1",
            "video": "",
            "fm": "",
            "link_url": "",
            "publish_time": "0",
            "view": "12.2w",
            "share": "http://static.owspace.com/wap/292590.html",
            "comment": "48",
            "good": "113",
            "bookmark": "0",
            "show_uid": "340875",
            "fm_play": "",
            "lunar_type": "1",
            "html5": "http://static.owspace.com/wap/292590.html",
            "author": "威廉·特雷弗",
            "tpl": 1,
            "avatar": "http://img.owspace.com/Public/static/avatar/3.png",
            "discover": "0",
            "category": "TO READ",
            "hot_comments": [],
            "parseXML": 1
        },
        {
            "id": "292009",
            "uid": "230357",
            "name": "",
            "title": "如果北京城\r\n可以折叠",
            "excerpt": "中国作家郝景芳的作品《北京折叠》刚刚获得世界科幻文学雨果奖。由作者本人授权，我们重刊此文，再次进入那座拥有三重空间的幻想之城。",
            "lead": "故事中的北京是一座可折叠的城市，大地和建筑定时翻转、折叠，小心翼翼地分隔出3个生存条件差异极大的空间。少数人在第一空间的蓝天下过着优渥的生活；多数人挣扎在拥挤不堪的第三空间，难以向第二、第一空间流动，连捡垃圾都是难能获得的工作。\r\n垃圾工老刀为了挣钱供孩子上学，冒险接活前往第一空间，目睹跨空间的残忍差距，甚至险遭意外……\r\n",
            "model": "1",
            "position": "0",
            "thumbnail": "http://img.owspace.com/Public/uploads/Picture/2016-08-21/57b9a10158d65.png",
            "create_time": "1471782840",
            "update_time": "2016/08/21",
            "tags": [
                {
                    "name": "北京折叠"
                },
                {
                    "name": "科幻"
                }
            ],
            "status": "1",
            "video": "",
            "fm": "",
            "link_url": "",
            "publish_time": "0",
            "view": "17.2w",
            "share": "http://static.owspace.com/wap/292009.html",
            "comment": "146",
            "good": "418",
            "bookmark": "0",
            "show_uid": "230357",
            "fm_play": "",
            "lunar_type": "1",
            "html5": "http://static.owspace.com/wap/292009.html",
            "author": "郝景芳",
            "tpl": 1,
            "avatar": "http://img.owspace.com/Public/static/avatar/2.png",
            "discover": "0",
            "category": "TO READ",
            "hot_comments": [],
            "parseXML": 1
        },
        {
            "id": "292381",
            "uid": "311091",
            "name": "",
            "title": "幸福过了头",
            "excerpt": "作家艾丽丝·门罗擅长描绘女性和家庭，她的作品《幸福过了头》并非人间喜剧，而只有平凡生活。在残酷而真实的世界里，故事里的她们各带伤疤，清醒地活着。",
            "lead": "他相信自己坠入爱河，她说这是只是孩子气的病；她以为是结伴旅途中的小坎，他明白这是长路的终结。他们曾经的欢乐，已经到了头。",
            "model": "1",
            "position": "0",
            "thumbnail": "http://img.owspace.com/Public/uploads/Picture/2016-08-03/57a19f372b168.jpg",
            "create_time": "1470355200",
            "update_time": "2016/08/05",
            "tags": [
                {
                    "name": "艾丽丝·门罗"
                },
                {
                    "name": "爱情"
                },
                {
                    "name": "婚姻"
                }
            ],
            "status": "1",
            "video": "",
            "fm": "",
            "link_url": "",
            "publish_time": "0",
            "view": "8.3w",
            "share": "http://static.owspace.com/wap/292381.html",
            "comment": "39",
            "good": "99",
            "bookmark": "0",
            "show_uid": "311091",
            "fm_play": "",
            "lunar_type": "1",
            "html5": "http://static.owspace.com/wap/292381.html",
            "author": "艾丽丝·门罗",
            "tpl": 1,
            "avatar": "http://img.owspace.com/Public/static/avatar/2.png",
            "discover": "0",
            "category": "TO READ",
            "hot_comments": [],
            "parseXML": 1
        },
        {
            "id": "292333",
            "uid": "294503",
            "name": "",
            "title": "爱国的自大",
            "excerpt": "百年前，中国人甲乙丙丁都有自己的爱国办法，但总结起来不过是一种自大。鲁迅为这些爱国者开出“不长进的民族”的疗救方法。这剂药在今天疗效是否依旧？",
            "lead": "《热风》是鲁迅写于1918年到1924年的杂文集。当时中国处在最黑暗的时代。鲁迅在“题记”中说：我觉得周围的空气太寒冽了，我自说我的话，所以反而称之曰《热风》。“救国救民需先救思想”今天分享这篇，鲁迅为合群的爱国的中国人开药。",
            "model": "1",
            "position": "0",
            "thumbnail": "http://img.owspace.com/Public/uploads/Picture/2016-07-22/5791e9ba77a69.jpg",
            "create_time": "1470182400",
            "update_time": "2016/08/03",
            "tags": [
                {
                    "name": "鲁迅"
                },
                {
                    "name": "爱国"
                },
                {
                    "name": "中国人"
                }
            ],
            "status": "1",
            "video": "",
            "fm": "",
            "link_url": "",
            "publish_time": "0",
            "view": "11w",
            "share": "http://static.owspace.com/wap/292333.html",
            "comment": "80",
            "good": "207",
            "bookmark": "0",
            "show_uid": "294503",
            "fm_play": "",
            "lunar_type": "1",
            "html5": "http://static.owspace.com/wap/292333.html",
            "author": "鲁迅",
            "tpl": 1,
            "avatar": "http://img.owspace.com/Public/static/avatar/4.png",
            "discover": "0",
            "category": "TO READ",
            "hot_comments": [],
            "parseXML": 1
        },
        {
            "id": "292366",
            "uid": "305981",
            "name": "",
            "title": "巴西\r\n未来之国",
            "excerpt": "世界的未来属于谁？属于美国、欧洲、还是中国？六十年前，茨威格曾预言巴西才是人类的“未来之国”，今天，他的预言实现了吗？",
            "lead": "1933 年希特勒上台，犹太裔奥地利作家茨威格也踏上了他的海外流亡生活，辗转英国，他定居巴西，并最终于 1942 年在他热爱的巴西服毒自杀。《巴西：未来之国》是茨威格关于巴西的著作，寄托了茨威格对人类文明的全部希望，他盛赞巴西是“未来之国”，而欧洲已是“昨日的世界”。书中对于巴西民族和他们的性格有详细的描述，茨威格认为巴西民族并非欧洲人认为的那样野蛮，而是天生敏感、热爱和平、喜爱思考，而巴西融合型民族的特征也让人看到了民族和解的可能，这恰恰是当时欧洲缺少的。",
            "model": "1",
            "position": "0",
            "thumbnail": "http://img.owspace.com/Public/uploads/Picture/2016-07-29/579b213e98ad2.png",
            "create_time": "1470009600",
            "update_time": "2016/08/01",
            "tags": [
                {
                    "name": "巴西"
                },
                {
                    "name": "茨威格"
                }
            ],
            "status": "1",
            "video": "",
            "fm": "",
            "link_url": "",
            "publish_time": "0",
            "view": "7.4w",
            "share": "http://static.owspace.com/wap/292366.html",
            "comment": "51",
            "good": "70",
            "bookmark": "0",
            "show_uid": "305981",
            "fm_play": "",
            "lunar_type": "1",
            "html5": "http://static.owspace.com/wap/292366.html",
            "author": "斯蒂芬·茨威格",
            "tpl": 1,
            "avatar": "http://img.owspace.com/Public/static/avatar/3.png",
            "discover": "0",
            "category": "TO READ",
            "hot_comments": [],
            "parseXML": 1
        },
        {
            "id": "292330",
            "uid": "293558",
            "name": "",
            "title": "大城市的\r\n死与生",
            "excerpt": "作者简·雅各布斯关于城市的理念曾改变北美城市发展方式，甚至超越城市规划范畴而影响时代精神。而这些经验是否能作用于现今中国城市的发展？",
            "lead": "上半年北京核心区人口减少，上海人口负增长，广州人口增速阶段性放缓，人口拐点似乎悄然来临。是时候关注我们城市的复兴与未来。以史为镜，可知兴替。我们城市今天所面临的很多问题，正是美国当年所经历的。今天，分享《美国大城市的死与生》序言的节选。",
            "model": "1",
            "position": "0",
            "thumbnail": "http://img.owspace.com/Public/uploads/Picture/2016-07-21/5790a1f520b8e.jpg",
            "create_time": "1469491200",
            "update_time": "2016/07/26",
            "tags": [
                {
                    "name": "美国"
                },
                {
                    "name": "简·雅各布斯"
                },
                {
                    "name": "城市规划"
                }
            ],
            "status": "1",
            "video": "",
            "fm": "",
            "link_url": "",
            "publish_time": "0",
            "view": "4.9w",
            "share": "http://static.owspace.com/wap/292330.html",
            "comment": "16",
            "good": "64",
            "bookmark": "0",
            "show_uid": "293558",
            "fm_play": "",
            "lunar_type": "1",
            "html5": "http://static.owspace.com/wap/292330.html",
            "author": "简·雅各布斯",
            "tpl": 1,
            "avatar": "http://img.owspace.com/Public/static/avatar/3.png",
            "discover": "0",
            "category": "TO READ",
            "hot_comments": [],
            "parseXML": 1
        },
        {
            "id": "292323",
            "uid": "292279",
            "name": "",
            "title": "文学和极权主义",
            "excerpt": "自由资本主义走到尽头，极权主义将人们关在一个人造的世界里，它的控制从思想侵入到文学中，让独立自主的个人不再存在。",
            "lead": "奥威尔希望集体化的经济不要发展成极权主义的社会形式，自由经济消失以后思想自由仍能够维持下去。“这是任何一个关心文学的人能抱的唯一希望。”",
            "model": "1",
            "position": "0",
            "thumbnail": "http://img.owspace.com/Public/uploads/Picture/2016-07-20/578f043840fd2.jpg",
            "create_time": "1469145600",
            "update_time": "2016/07/22",
            "tags": [
                {
                    "name": "奥威尔"
                },
                {
                    "name": "极权主义"
                },
                {
                    "name": "文学"
                }
            ],
            "status": "1",
            "video": "",
            "fm": "",
            "link_url": "",
            "publish_time": "0",
            "view": "3.5w",
            "share": "http://static.owspace.com/wap/292323.html",
            "comment": "28",
            "good": "77",
            "bookmark": "0",
            "show_uid": "292279",
            "fm_play": "",
            "lunar_type": "1",
            "html5": "http://static.owspace.com/wap/292323.html",
            "author": "乔治·奥威尔",
            "tpl": 1,
            "avatar": "http://img.owspace.com/Public/static/avatar/1.png",
            "discover": "0",
            "category": "TO READ",
            "hot_comments": [],
            "parseXML": 1
        },
        {
            "id": "292319",
            "uid": "290169",
            "name": "",
            "title": "愿我的国家\r\n与正义同在",
            "excerpt": "“您不爱您的国家”，加缪的友人曾经这样指责他，从那时起他们就分道扬镳。五年后，加缪用一封长信告诉这位德国友人，什么是对国家真正的爱。",
            "lead": "《致一位德国友人的信》写于1943年，法国维西傀儡政府被纳粹德国控制，戴高乐与德国在突尼斯交战。加缪在信中预言正是因为德国人对于国家盲目的爱，终将使德国失败。",
            "model": "1",
            "position": "0",
            "thumbnail": "http://img.owspace.com/Public/uploads/Picture/2016-07-20/578ed2176f545.jpg",
            "create_time": "1468972800",
            "update_time": "2016/07/20",
            "tags": [
                {
                    "name": "加缪"
                },
                {
                    "name": "国家"
                },
                {
                    "name": "历史"
                },
                {
                    "name": "政治"
                },
                {
                    "name": "思想"
                }
            ],
            "status": "1",
            "video": "",
            "fm": "",
            "link_url": "",
            "publish_time": "0",
            "view": "5.5w",
            "share": "http://static.owspace.com/wap/292319.html",
            "comment": "42",
            "good": "125",
            "bookmark": "0",
            "show_uid": "290169",
            "fm_play": "",
            "lunar_type": "1",
            "html5": "http://static.owspace.com/wap/292319.html",
            "author": "阿尔贝·加缪",
            "tpl": 1,
            "avatar": "http://img.owspace.com/Public/static/avatar/2.png",
            "discover": "0",
            "category": "TO READ",
            "hot_comments": [],
            "parseXML": 1
        },
        {
            "id": "292274",
            "uid": "277643",
            "name": "",
            "title": "大学生",
            "excerpt": "《大学生》是契诃夫自己最喜欢的短篇小说。当刺骨寒风、贫穷、饥饿一同向大学生袭来，温暖火焰的存在给予信仰和希望一线生机。",
            "lead": "这是编辑权力交到读者手上的第一天。",
            "model": "1",
            "position": "0",
            "thumbnail": "http://img.owspace.com/Public/uploads/Picture/2016-07-07/577e3be029f42.jpg",
            "create_time": "1468800000",
            "update_time": "2016/07/18",
            "tags": [
                {
                    "name": "契诃夫"
                },
                {
                    "name": "大学生"
                },
                {
                    "name": "黄灿然推荐"
                }
            ],
            "status": "1",
            "video": "",
            "fm": "",
            "link_url": "",
            "publish_time": "0",
            "view": "5.3w",
            "share": "http://static.owspace.com/wap/292274.html",
            "comment": "47",
            "good": "105",
            "bookmark": "0",
            "show_uid": "277643",
            "fm_play": "",
            "lunar_type": "1",
            "html5": "http://static.owspace.com/wap/292274.html",
            "author": "契诃夫",
            "tpl": 1,
            "avatar": "http://img.owspace.com/Public/static/avatar/4.png",
            "discover": "0",
            "category": "TO READ",
            "hot_comments": [],
            "parseXML": 1
        },
        {
            "id": "292255",
            "uid": "273730",
            "name": "",
            "title": "基督造访\r\n魔鬼降临",
            "excerpt": "米恩斯继承了卡佛等人的传统，专注地用短篇小说记录当代美国社会。他笔下生活着一群社会边缘人。糅合抒情与幽默，他描述一个具有普世性的人类困境。",
            "lead": "要么关于犯罪、死亡；要么是被世界抛弃的绝望，米恩斯从来不贩卖励志和温情。他用不同故事一遍又一遍地重复论述着：人是如何失去与生活的联系。",
            "model": "1",
            "position": "0",
            "thumbnail": "http://img.owspace.com/Public/uploads/Picture/2016-07-01/5776350262098.jpg",
            "create_time": "1467590400",
            "update_time": "2016/07/04",
            "tags": [
                {
                    "name": "短篇"
                },
                {
                    "name": "美国社会"
                }
            ],
            "status": "1",
            "video": "",
            "fm": "",
            "link_url": "",
            "publish_time": "0",
            "view": "3w",
            "share": "http://static.owspace.com/wap/292255.html",
            "comment": "23",
            "good": "78",
            "bookmark": "0",
            "show_uid": "273730",
            "fm_play": "",
            "lunar_type": "1",
            "html5": "http://static.owspace.com/wap/292255.html",
            "author": "大卫·米恩斯",
            "tpl": 1,
            "avatar": "http://img.owspace.com/Public/static/avatar/1.png",
            "discover": "0",
            "category": "TO READ",
            "hot_comments": [],
            "parseXML": 1
        },
        {
            "id": "292256",
            "uid": "273773",
            "name": "",
            "title": "橄榄树林的\r\n悲风",
            "excerpt": "“吉他的呜咽，开始了。黎明的酒杯，碎了。”年轻的洛尔迦作为诗人的首次亮相就惊艳四座。然而这位20世纪西班牙最伟大的诗人却在38年的短暂光芒后逝去。",
            "lead": "1936 年 8 月 15 日凌晨，破晓之前，一声枪响，年轻的洛尔迦倒在了橄榄林边一片荒凉的空地上。这一年，他 38 岁，还在回望童年，却被迫搅进政治恶局，并由此丧命。北岛逐一梳理了洛尔迦的诗歌和人生，下文为文章节选。",
            "model": "1",
            "position": "0",
            "thumbnail": "http://img.owspace.com/Public/uploads/Picture/2016-07-01/57764ec662f19.jpg",
            "create_time": "1467419460",
            "update_time": "2016/07/02",
            "tags": [
                {
                    "name": "洛尔迦"
                },
                {
                    "name": "北岛"
                },
                {
                    "name": "诗歌评论"
                }
            ],
            "status": "1",
            "video": "",
            "fm": "",
            "link_url": "",
            "publish_time": "0",
            "view": "3.6w",
            "share": "http://static.owspace.com/wap/292256.html",
            "comment": "7",
            "good": "64",
            "bookmark": "0",
            "show_uid": "273773",
            "fm_play": "",
            "lunar_type": "1",
            "html5": "http://static.owspace.com/wap/292256.html",
            "author": "北岛",
            "tpl": 1,
            "avatar": "http://img.owspace.com/Public/static/avatar/4.png",
            "discover": "0",
            "category": "TO READ",
            "hot_comments": [],
            "parseXML": 1
        },
        {
            "id": "292113",
            "uid": "250691",
            "name": "",
            "title": "把所有感情\r\n寄往查令街",
            "excerpt": "如果你们恰好路过查令十字街 84 号，请代我献上一吻，我亏欠它良多。二十年里，我通过书信和这家书店老板、员工交流、向他们买书，却未能一见。",
            "lead": "海莲是个热爱旧书的纽约作家，在物质贫乏的年代，她在阅读中找到心灵寄托。纽约的书店无法满足她需求，而一间伦敦旧书店的广告很快吸引了她。从此她和书店主管法兰克以及所有员工，透过书信展开数十年的订书、买书历程，还有心灵与情感的交流。",
            "model": "1",
            "position": "0",
            "thumbnail": "http://img.owspace.com/Public/uploads/Picture/2016-05-27/57482e5709911.jpg",
            "create_time": "1465689600",
            "update_time": "2016/06/12",
            "tags": [
                {
                    "name": "爱书人的圣经"
                },
                {
                    "name": "查令十字街84号"
                }
            ],
            "status": "1",
            "video": "",
            "fm": "",
            "link_url": "",
            "publish_time": "0",
            "view": "6.2w",
            "share": "http://static.owspace.com/wap/292113.html",
            "comment": "89",
            "good": "232",
            "bookmark": "0",
            "show_uid": "250691",
            "fm_play": "",
            "lunar_type": "1",
            "html5": "http://static.owspace.com/wap/292113.html",
            "author": "海莲·汉芙",
            "tpl": 1,
            "avatar": "http://img.owspace.com/Public/static/avatar/4.png",
            "discover": "0",
            "category": "TO READ",
            "hot_comments": [],
            "parseXML": 1
        },
        {
            "id": "292111",
            "uid": "250382",
            "name": "",
            "title": "为什么\r\n我常常沉默",
            "excerpt": "被称为““现代诗歌第一人”的他曾经写：“我傲然生活了几十年，\r\n仿佛曾做着万物的导演；实则在它们永久的秩序下，我只当一会儿小小的演员”。",
            "lead": "十六岁时，查良铮将他的姓拆成木旦，为自己取笔名穆旦，从此开始创作、翻译生涯。他写的诗意象离奇，抽象、具象结合。周末，我们翻出他的诗作两首，一探这位“现代诗歌第一人”的内在。",
            "model": "1",
            "position": "0",
            "thumbnail": "http://img.owspace.com/Public/uploads/Picture/2016-05-27/57480751d0e67.jpg",
            "create_time": "1464393600",
            "update_time": "2016/05/28",
            "tags": [
                {
                    "name": "诗歌"
                },
                {
                    "name": "穆旦"
                }
            ],
            "status": "1",
            "video": "",
            "fm": "",
            "link_url": "",
            "publish_time": "0",
            "view": "9w",
            "share": "http://static.owspace.com/wap/292111.html",
            "comment": "56",
            "good": "312",
            "bookmark": "0",
            "show_uid": "250382",
            "fm_play": "",
            "lunar_type": "1",
            "html5": "http://static.owspace.com/wap/292111.html",
            "author": "穆旦",
            "tpl": 1,
            "avatar": "http://img.owspace.com/Public/static/avatar/1.png",
            "discover": "0",
            "category": "TO READ",
            "hot_comments": [],
            "parseXML": 1
        },
        {
            "id": "292104",
            "uid": "249321",
            "name": "",
            "title": "谁住在\r\n17年前的北京",
            "excerpt": "北京南城牛街一胡同区年内将拆迁，西城动物园服装批发市场也将搬撤，一片又一片老地方在北京地图上灭迹，想起17年前的“东村”，看艺术家荣荣当年日记。",
            "lead": "这个名叫“大山庄”的北京破村，最终在 2001年和 2002年被拆，融入到日益扩大的首都繁花版图。因为普通、陈旧、和破败，它的消失没在京城居民中激起任何让人侧目的轰动。但它的另一别名——“东村”——在中国艺术史里声名远扬。",
            "model": "1",
            "position": "0",
            "thumbnail": "http://img.owspace.com/Public/uploads/Picture/2016-05-26/574679b126e4b.jpg",
            "create_time": "1464307200",
            "update_time": "2016/05/27",
            "tags": [
                {
                    "name": "东村"
                },
                {
                    "name": "艺术"
                }
            ],
            "status": "1",
            "video": "",
            "fm": "",
            "link_url": "",
            "publish_time": "0",
            "view": "6.1w",
            "share": "http://static.owspace.com/wap/292104.html",
            "comment": "31",
            "good": "86",
            "bookmark": "0",
            "show_uid": "249321",
            "fm_play": "",
            "lunar_type": "1",
            "html5": "http://static.owspace.com/wap/292104.html",
            "author": "巫鸿",
            "tpl": 1,
            "avatar": "http://img.owspace.com/Public/static/avatar/3.png",
            "discover": "0",
            "category": "TO READ",
            "hot_comments": [],
            "parseXML": 1
        },
        {
            "id": "292087",
            "uid": "246787",
            "name": "",
            "title": "像宋体字一样\r\n强悍地上班",
            "excerpt": "今天，论文写作、职场报告请用宋体，读书看报也多宋体——宋体字一统霸业，是中文书写界的“普通话”。其实，宋体字自出生就坚挺、跋扈，无论你喜欢与否。",
            "lead": "今天，宋体字已是打字、书报印刷的标准字体。历史上，它曾是“救星”——摧枯拉朽般降低了印刷书的生产成本。在印刷术被发明和应用后的很长一段时间内，手抄书依旧是书籍生产的主流，印刷书占比极少。主要因为印刷书成本太高，直到明代中期，宋体字的出现。",
            "model": "1",
            "position": "0",
            "thumbnail": "http://img.owspace.com/Public/uploads/Picture/2016-05-22/5741879d9d097.jpg",
            "create_time": "1463961600",
            "update_time": "2016/05/23",
            "tags": [
                {
                    "name": "文化"
                },
                {
                    "name": "宋体字"
                },
                {
                    "name": "书籍"
                }
            ],
            "status": "1",
            "video": "",
            "fm": "",
            "link_url": "",
            "publish_time": "0",
            "view": "6.1w",
            "share": "http://static.owspace.com/wap/292087.html",
            "comment": "38",
            "good": "64",
            "bookmark": "0",
            "show_uid": "246787",
            "fm_play": "",
            "lunar_type": "1",
            "html5": "http://static.owspace.com/wap/292087.html",
            "author": "周绍明",
            "tpl": 1,
            "avatar": "http://img.owspace.com/Public/static/avatar/3.png",
            "discover": "0",
            "category": "TO READ",
            "hot_comments": [],
            "parseXML": 1
        }
    ],
    "msg": "",
    "code": 0
}
